BonkersDB/__init__.py
BonkersDB-0.0.1.dist-info/LICENSE
BonkersDB-0.0.1.dist-info/METADATA
BonkersDB-0.0.1.dist-info/WHEEL
BonkersDB-0.0.1.dist-info/top_level.txt
BonkersDB-0.0.1.dist-info/RECORD
