Metadata-Version: 2.1
Name: BonkersDB
Version: 0.0.1
Summary: BonkersDB
Home-page: https://replit.com/@A1PHA1/BonkersDB
Author: Vivaan S.
Author-email: vivaan@blabbr.xyz
License: UNKNOWN
Platform: UNKNOWN
Classifier: Programming Language :: Python :: 3
Classifier: License :: OSI Approved :: MIT License
Classifier: Operating System :: OS Independent
Requires-Python: >=3.6
